odoo/addons/pos_cash_control_multiple_config/README.rst
odoo/addons/pos_cash_control_multiple_config/__init__.py
odoo/addons/pos_cash_control_multiple_config/__manifest__.py
odoo/addons/pos_cash_control_multiple_config/i18n/pos_cash_control_multiple_config.pot
odoo/addons/pos_cash_control_multiple_config/models/__init__.py
odoo/addons/pos_cash_control_multiple_config/models/account_bank_statement.py
odoo/addons/pos_cash_control_multiple_config/models/pos_session.py
odoo/addons/pos_cash_control_multiple_config/readme/CONTRIBUTORS.rst
odoo/addons/pos_cash_control_multiple_config/readme/DESCRIPTION.rst
odoo/addons/pos_cash_control_multiple_config/static/description/icon.png
odoo/addons/pos_cash_control_multiple_config/static/description/index.html
odoo12_addon_pos_cash_control_multiple_config-12.0.1.0.2.dist-info/METADATA
odoo12_addon_pos_cash_control_multiple_config-12.0.1.0.2.dist-info/WHEEL
odoo12_addon_pos_cash_control_multiple_config-12.0.1.0.2.dist-info/top_level.txt
odoo12_addon_pos_cash_control_multiple_config-12.0.1.0.2.dist-info/RECORD
