Metadata-Version: 2.1
Name: odoo12-addon-pos-cash-control-multiple-config
Version: 12.0.1.0.2
Summary: Handle correctly opening balance in a multi point of sale context with Cash control enabled.
Home-page: https://github.com/OCA/pos
Author: GRAP, Odoo Community Association (OCA)
Author-email: support@odoo-community.org
License: AGPL-3
Platform: UNKNOWN
Classifier: Programming Language :: Python
Classifier: Framework :: Odoo
Classifier: License :: OSI Approved :: GNU Affero General Public License v3
Requires-Python: >=3.5
Requires-Dist: odoo (<12.1dev,>=12.0a)
